LICENSE
MANIFEST.in
README.md
pyproject.toml
setup.cfg
setup.py
../LICENSE
../README.md
caretaker/__init__.py
caretaker/settings.py
caretaker/urls.py
caretaker/views.py
caretaker/backend/__init__.py
caretaker/backend/abstract_backend.py
caretaker/backend/backends/__init__.py
caretaker/backend/backends/local.py
caretaker/backend/backends/s3.py
caretaker/backend/backends/terraform_aws/__init__.py
caretaker/backend/backends/terraform_aws/main.tf
caretaker/backend/backends/terraform_aws/output.tf
caretaker/backend/backends/terraform_aws/__pycache__/__init__.cpython-310.pyc
caretaker/frontend/__init__.py
caretaker/frontend/abstract_frontend.py
caretaker/frontend/frontends/__init__.py
caretaker/frontend/frontends/django.py
caretaker/frontend/frontends/utils.py
caretaker/frontend/frontends/database_exporters/__init__.py
caretaker/frontend/frontends/database_exporters/abstract_database_exporter.py
caretaker/frontend/frontends/database_exporters/django/__init__.py
caretaker/frontend/frontends/database_exporters/django/mysql.py
caretaker/frontend/frontends/database_exporters/django/postgres.py
caretaker/frontend/frontends/database_exporters/django/sqlite.py
caretaker/frontend/frontends/database_exporters/django/utils.py
caretaker/frontend/frontends/database_importers/__init__.py
caretaker/frontend/frontends/database_importers/abstract_database_importer.py
caretaker/frontend/frontends/database_importers/django/__init__.py
caretaker/frontend/frontends/database_importers/django/mysql.py
caretaker/frontend/frontends/database_importers/django/postgres.py
caretaker/frontend/frontends/database_importers/django/sqlite.py
caretaker/management/__init__.py
caretaker/management/commands/__init__.py
caretaker/management/commands/create_backup.py
caretaker/management/commands/export_sql.py
caretaker/management/commands/get_terraform.py
caretaker/management/commands/import_backup.py
caretaker/management/commands/install_cron.py
caretaker/management/commands/list_backups.py
django_caretaker.egg-info/PKG-INFO
django_caretaker.egg-info/SOURCES.txt
django_caretaker.egg-info/dependency_links.txt
django_caretaker.egg-info/requires.txt
django_caretaker.egg-info/top_level.txt